ens_permissions/__init__.py
ens_permissions/chaindata.py
ens_permissions/graph.py
ens_permissions/roles.py
ens_permissions/utils.py
ens_permissions/contracts/IAccessControl.json
ens_permissions-0.2.1.dist-info/LICENSE.txt
ens_permissions-0.2.1.dist-info/METADATA
ens_permissions-0.2.1.dist-info/WHEEL
ens_permissions-0.2.1.dist-info/top_level.txt
ens_permissions-0.2.1.dist-info/RECORD
