Metadata-Version: 2.1
Name: ens-permissions
Version: 0.2.1
Summary: Add a short description here!
Home-page: https://github.com/pyscaffold/pyscaffold/
Author: Ensuro
Author-email: dev@ensuro.co
License: MIT
Project-URL: Documentation, https://pyscaffold.org/
Platform: any
Classifier: Development Status :: 4 - Beta
Classifier: Programming Language :: Python
License-File: LICENSE.txt
Requires-Dist: eth-prototype[web3]
Requires-Dist: graphviz
Requires-Dist: importlib-metadata ; python_version < "3.8"
Provides-Extra: testing
Requires-Dist: setuptools ; extra == 'testing'
Requires-Dist: pytest ; extra == 'testing'
Requires-Dist: pytest-cov ; extra == 'testing'
